{
  "metadata": {
    "id": "golden-circle",
    "name": "◯ Golden Circle",
    "description": "Fibonacci-based proportions with sophisticated organic elegance and mathematical harmony",
    "author": "ReFlow",
    "version": "1.0.0",
    "tags": ["golden-ratio", "fibonacci", "mathematical", "elegant", "circle"]
  },
  "parameters": {
    "circleStyle": {
      "type": "select",
      "default": 0,
      "options": [
        { "value": 0, "label": "⭕ Perfect Circle" },
        { "value": 1, "label": "🌿 Organic" },
        { "value": 2, "label": "🐚 Fibonacci Spiral" },
        { "value": 3, "label": "⬡ Segmented" },
        { "value": 4, "label": "💫 Breathing" }
      ],
      "label": "Circle Style",
      "category": "Style"
    },
    "goldenProportion": {
      "type": "slider",
      "default": 1.618,
      "min": 0.5,
      "max": 2,
      "step": 0.05,
      "label": "Golden Proportion",
      "category": "Mathematics"
    },
    "fibonacciInfluence": {
      "type": "slider",
      "default": 0.3,
      "min": 0,
      "max": 1,
      "step": 0.05,
      "label": "Fibonacci Influence",
      "category": "Mathematics"
    },
    "organicVariation": {
      "type": "slider",
      "default": 0.08,
      "min": 0,
      "max": 0.3,
      "step": 0.01,
      "label": "Organic Variation",
      "category": "Geometry"
    },
    "mathematicalPurity": {
      "type": "slider",
      "default": 0.9,
      "min": 0.7,
      "max": 1,
      "step": 0.01,
      "label": "Mathematical Purity",
      "category": "Mathematics"
    },
    "concentricLayers": {
      "type": "slider",
      "default": 1,
      "min": 1,
      "max": 4,
      "step": 1,
      "label": "Concentric Layers",
      "category": "Geometry"
    },
    "spiralTightness": {
      "type": "slider",
      "default": 0.8,
      "min": 0.1,
      "max": 2,
      "step": 0.1,
      "label": "Spiral Tightness",
      "category": "Geometry"
    },
    "fillStyle": {
      "type": "select",
      "default": "radial",
      "options": [
        { "value": "none", "label": "🚫 None" },
        { "value": "solid", "label": "⬜ Solid" },
        { "value": "radial", "label": "🎯 Radial" },
        { "value": "fibonacci", "label": "🐚 Fibonacci" }
      ],
      "label": "Fill Style",
      "category": "Appearance"
    },
    "colorMode": {
      "type": "select",
      "default": "theme",
      "options": [
        { "value": "theme", "label": "🎨 Theme" },
        { "value": "golden", "label": "🌟 Golden" },
        { "value": "custom", "label": "🔧 Custom" }
      ],
      "label": "Color Mode",
      "category": "Color"
    },
    "warmth": {
      "type": "slider",
      "default": 0.7,
      "min": 0.3,
      "max": 1,
      "step": 0.05,
      "label": "Warmth",
      "category": "Color"
    },
    "sophistication": {
      "type": "slider",
      "default": 0.6,
      "min": 0.4,
      "max": 0.9,
      "step": 0.05,
      "label": "Sophistication",
      "category": "Color"
    },
    "innerGlow": {
      "type": "slider",
      "default": 0.15,
      "min": 0,
      "max": 0.4,
      "step": 0.05,
      "label": "Inner Glow",
      "category": "Effects"
    },
    "breathingMotion": {
      "type": "slider",
      "default": 0.05,
      "min": 0,
      "max": 0.2,
      "step": 0.02,
      "label": "Breathing Motion",
      "category": "Animation"
    }
  }
}